jupytercustomsort/__init__.py
jupytercustomsort/nbext/main.js
jupytercustomsort-0.1.1.dist-info/LICENSE
jupytercustomsort-0.1.1.dist-info/METADATA
jupytercustomsort-0.1.1.dist-info/WHEEL
jupytercustomsort-0.1.1.dist-info/top_level.txt
jupytercustomsort-0.1.1.dist-info/RECORD
